examplebtug5/__init__.py
examplebtug5/example.py
examplebtug5-0.0.1.dist-info/LICENSE.txt
examplebtug5-0.0.1.dist-info/METADATA
examplebtug5-0.0.1.dist-info/WHEEL
examplebtug5-0.0.1.dist-info/top_level.txt
examplebtug5-0.0.1.dist-info/RECORD
